PriceAnomalyTracker.py
PriceAnomalyTracker-1.1.3.dist-info/LICENSE
PriceAnomalyTracker-1.1.3.dist-info/METADATA
PriceAnomalyTracker-1.1.3.dist-info/WHEEL
PriceAnomalyTracker-1.1.3.dist-info/top_level.txt
PriceAnomalyTracker-1.1.3.dist-info/RECORD
