Metadata-Version: 2.1
Name: PriceAnomalyTracker
Version: 1.1.3
Summary: PriceAnomalyTracker is a Python library for detecting anomalies in time series data. Using unsupervised learning methods, it applies clustering techniques (such as K-Means and DBSCAN) and normality tests (such as the Shapiro Test) to identify anomalies in a wide range of data.
Home-page: https://github.com/RobertoJuniorXYZ/PriceAnomalyTracker
Author: Roberto Junior
Author-email: robertocarlosifrj@gmail.com
License: MIT License
Project-URL: Documentation, https://github.com/RobertoJuniorXYZ/PriceAnomalyTracker/wiki
Project-URL: PyPI, https://pypi.org/project/PriceAnomalyTracker/
Project-URL: Source, https://github.com/RobertoJuniorXYZ/PriceAnomalyTracker/
Keywords: price anomaly tracker
License-File: LICENSE
Requires-Dist: numpy
Requires-Dist: scikit-learn
Requires-Dist: scipy
